pollination/well_daylight/__init__.py
pollination/well_daylight/_process_epw.py
pollination/well_daylight/_visualization.py
pollination/well_daylight/entry.py
pollination_well_daylight-0.0.15.dist-info/LICENSE
pollination_well_daylight-0.0.15.dist-info/METADATA
pollination_well_daylight-0.0.15.dist-info/WHEEL
pollination_well_daylight-0.0.15.dist-info/top_level.txt
pollination_well_daylight-0.0.15.dist-info/RECORD
