Metadata-Version: 2.1
Name: pollination-well-daylight
Version: 0.0.15
Summary: WELL daylight recipe for Pollination.
Home-page: https://github.com/pollination/well-daylight
Author: pollination
Author-email: info@pollination.solutions
Maintainer: mikkel, pollination
Maintainer-email: mikkel@ladybug.tools, info@pollination.solutions
License: PolyForm Shield License 1.0.0, https://polyformproject.org/wp-content/uploads/2020/06/PolyForm-Shield-1.0.0.txt
Project-URL: icon, https://raw.githubusercontent.com/ladybug-tools/artwork/master/icons_components/honeybee/png/welldaylight.png
Project-URL: docker, https://hub.docker.com/r/ladybugtools/honeybee-radiance
Keywords: honeybee,radiance,ladybug-tools,daylight,annual-daylight,well,well-daylight
License-File: LICENSE
Requires-Dist: pollination-two-phase-daylight-coefficient>=1.1.59
Requires-Dist: pollination-ladybug>=0.2.4
Requires-Dist: pollination-honeybee-display>=0.1.17
